sarfile/__init__.py
sarfile/_cli.py
sarfile/_compress.py
sarfile/_constants.py
sarfile/_header.py
sarfile/_item.py
sarfile/_sarfile.py
sarfile/py.typed
sarfile-0.1.7.dist-info/LICENSE
sarfile-0.1.7.dist-info/METADATA
sarfile-0.1.7.dist-info/WHEEL
sarfile-0.1.7.dist-info/entry_points.txt
sarfile-0.1.7.dist-info/top_level.txt
sarfile-0.1.7.dist-info/RECORD
